{
  "version": "6",
  "dialect": "sqlite",
  "id": "06fde771-b209-42ca-98f0-6bd0e8a9d795",
  "prevId": "00000000-0000-0000-0000-000000000000",
  "tables": {
    "profiles": {
      "name": "profiles",
      "columns": {
        "did": {
          "name": "did",
          "type": "text",
          "primaryKey": true,
          "notNull": true,
          "autoincrement": false
        },
        "display_name": {
          "name": "display_name",
          "type": "text(640)",
          "primaryKey": false,
          "notNull": true,
          "autoincrement": false
        },
        "description": {
          "name": "description",
          "type": "text(2560)",
          "primaryKey": false,
          "notNull": false,
          "autoincrement": false
        },
        "avatar_cid": {
          "name": "avatar_cid",
          "type": "text",
          "primaryKey": false,
          "notNull": false,
          "autoincrement": false
        },
        "created_at": {
          "name": "created_at",
          "type": "text",
          "primaryKey": false,
          "notNull": true,
          "autoincrement": false
        },
        "indexed_at": {
          "name": "indexed_at",
          "type": "text",
          "primaryKey": false,
          "notNull": false,
          "autoincrement": false,
          "default": "(CURRENT_TIMESTAMP)"
        }
      },
      "indexes": {},
      "foreignKeys": {},
      "compositePrimaryKeys": {},
      "uniqueConstraints": {},
      "checkConstraints": {}
    }
  },
  "views": {},
  "enums": {},
  "_meta": {
    "schemas": {},
    "tables": {},
    "columns": {}
  },
  "internal": {
    "indexes": {}
  }
}
